LICENSE
README.rst
setup.cfg
setup.py
cities_tiny/__init__.py
cities_tiny/admin.py
cities_tiny/models.py
cities_tiny/settings.py
cities_tiny/tests.py
cities_tiny/locale/ru/LC_MESSAGES/django.po
cities_tiny/management/__init__.py
cities_tiny/management/commands/__init__.py
cities_tiny/management/commands/citiestinyrefresh.py
django_cities_tiny.egg-info/PKG-INFO
django_cities_tiny.egg-info/SOURCES.txt
django_cities_tiny.egg-info/dependency_links.txt
django_cities_tiny.egg-info/not-zip-safe
django_cities_tiny.egg-info/top_level.txt