Metadata-Version: 1.0
Name: django-cities-tiny
Version: 1.0
Summary: Another simple alternative to django-cities
Home-page: http://code.google.com/p/django-cities-tiny/
Author: Konstantin Korikov (original by James Pic)
Author-email: lostclus@gmail.com
License: MIT
Keywords: django cities countries
Platform: UNKNOWN
Classifier: Development Status :: 3 - Alpha
Classifier: Environment :: Web Environment
Classifier: Framework :: Django
Classifier: Intended Audience :: Developers
Classifier: License :: OSI Approved :: MIT License
Classifier: Operating System :: OS Independent
Classifier: Programming Language :: Python
Classifier: Programming Language :: Python :: 2
Classifier: Topic :: Internet :: WWW/HTTP
Classifier: Topic :: Software Development :: Libraries :: Python Modules
